wikirate4py/__init__.py
wikirate4py/api.py
wikirate4py/cursor.py
wikirate4py/exceptions.py
wikirate4py/mixins.py
wikirate4py/models.py
wikirate4py/utils.py
wikirate4py-2.0.6.dist-info/LICENSE
wikirate4py-2.0.6.dist-info/METADATA
wikirate4py-2.0.6.dist-info/WHEEL
wikirate4py-2.0.6.dist-info/top_level.txt
wikirate4py-2.0.6.dist-info/zip-safe
wikirate4py-2.0.6.dist-info/RECORD
