Metadata-Version: 2.1
Name: wikirate4py
Version: 2.0.6
Summary: Wikirate for Python!
Home-page: https://github.com/wikirate/wikirate4py
Download-URL: https://github.com/wikirate/wikirate4py/archive/refs/tags/v2.0.6.tar.gz
Author: Vasiliki Gkatziaki
Author-email: vasso@wikirate.org
License: GPL-3.0
Project-URL: Documentation, https://wikirate4py.readthedocs.io
Project-URL: Issue Tracker, https://github.com/wikirate4py/wikirate4py/issues
Project-URL: Source Code, https://github.com/wikirate4py/wikirate4py
Keywords: wikirate library
Classifier: Development Status :: 5 - Production/Stable
Classifier: Topic :: Software Development :: Libraries
Classifier: License :: OSI Approved :: GNU General Public License v3 (GPLv3)
Classifier: Operating System :: OS Independent
Classifier: Programming Language :: Python
Classifier: Programming Language :: Python :: 3
Classifier: Programming Language :: Python :: 3.6
Classifier: Programming Language :: Python :: 3.7
Classifier: Programming Language :: Python :: 3.8
Classifier: Programming Language :: Python :: 3.9
Classifier: Programming Language :: Python :: 3 :: Only
Requires-Python: >=3.6
License-File: LICENSE
Requires-Dist: requests
Requires-Dist: html2text
Requires-Dist: pandas
Provides-Extra: test
Requires-Dist: mock ; extra == 'test'
Requires-Dist: nose ; extra == 'test'
Requires-Dist: vcrpy ; extra == 'test'
Requires-Dist: html2text ; extra == 'test'
Requires-Dist: python-dotenv ; extra == 'test'
